openchain_telco_sbom_validator/cli.py
openchain_telco_sbom_validator/reporter.py
openchain_telco_sbom_validator/validator.py
openchain_telco_sbom_validator-0.3.2.dist-info/licenses/LICENSE
openchain_telco_sbom_validator-0.3.2.dist-info/METADATA
openchain_telco_sbom_validator-0.3.2.dist-info/WHEEL
openchain_telco_sbom_validator-0.3.2.dist-info/entry_points.txt
openchain_telco_sbom_validator-0.3.2.dist-info/top_level.txt
openchain_telco_sbom_validator-0.3.2.dist-info/zip-safe
openchain_telco_sbom_validator-0.3.2.dist-info/RECORD
