Metadata-Version: 2.4
Name: openchain-telco-sbom-validator
Version: 0.3.2
Summary: Validator against versions 1.0 and 1.1 of the OpenChain Telco SBOM Guide
Home-page: https://github.com/OpenChain-Project/Telco-WG/tree/main/tools/openchain_telco_sbom_validator
Author: Gergely Csatari, Marc-Etienne Vargenau
Author-email: gergely.csatari@nokia.com, marc-etienne.vargenau@nokia.com
Project-URL: Bug Tracker, https://github.com/OpenChain-Project/Telco-WG/issues
Project-URL: repository, https://github.com/OpenChain-Project/Telco-WG/
Classifier: Development Status :: 1 - Planning
Classifier: Topic :: Software Development
Classifier: Topic :: Software Development :: Libraries
Classifier: Topic :: Communications :: Telephony
Classifier: Topic :: Communications
Classifier: Programming Language :: Python :: 3
Classifier: License :: OSI Approved :: Apache Software License
Classifier: Operating System :: OS Independent
Requires-Python: >=3.11
License-File: LICENSE
Requires-Dist: spdx-tools>=0.8.3
Requires-Dist: requests>=2.32.4
Requires-Dist: prettytable>=3.16.0
Requires-Dist: packageurl-python>=0.17.1
Requires-Dist: ntia-conformance-checker>=3.2.0
Requires-Dist: validators>=0.35.0
Dynamic: license-file
